enxima/__init__.py
enxima-0.1.0.dist-info/entry_points.txt
enxima-0.1.0.dist-info/METADATA
enxima-0.1.0.dist-info/WHEEL
enxima-0.1.0.dist-info/RECORD
